hyperdash/__init__.py
hyperdash/client.py
hyperdash/code_runner.py
hyperdash/commands.py
hyperdash/constants.py
hyperdash/hyper_dash.py
hyperdash/io_buffer.py
hyperdash/jupyter.py
hyperdash/jupyter_2_exec.py
hyperdash/jupyter_3_exec.py
hyperdash/sdk.py
hyperdash/sdk_message.py
hyperdash/server_manager.py
hyperdash-0.8.0.dist-info/DESCRIPTION.rst
hyperdash-0.8.0.dist-info/entry_points.txt
hyperdash-0.8.0.dist-info/METADATA
hyperdash-0.8.0.dist-info/metadata.json
hyperdash-0.8.0.dist-info/RECORD
hyperdash-0.8.0.dist-info/top_level.txt
hyperdash-0.8.0.dist-info/WHEEL
hyperdash_cli/__init__.py
hyperdash_cli/__main__.py
hyperdash_cli/cli-runner.py
hyperdash_cli/cli.py
hyperdash_cli/constants.py
